substratools/__init__.py
substratools/__version__.py
substratools/exceptions.py
substratools/function.py
substratools/opener.py
substratools/task_resources.py
substratools/utils.py
substratools/workspace.py
substratools-1.0.0.dist-info/METADATA
substratools-1.0.0.dist-info/WHEEL
substratools-1.0.0.dist-info/licenses/LICENSE
substratools-1.0.0.dist-info/RECORD
