Metadata-Version: 2.3
Name: substratools
Version: 1.0.0
Summary: Python tools to submit functions on the Substra platform
Project-URL: Documentation, https://docs.substra.org/en/stable/
Project-URL: Repository, https://github.com/Substra/substra-tools
Project-URL: Changelog, https://github.com/Substra/substra-tools/blob/main/CHANGELOG.md
Author: Owkin, Inc.
License: 
License-File: LICENSE
Keywords: substra
Classifier: Intended Audience :: Developers
Classifier: Natural Language :: English
Classifier: Operating System :: OS Independent
Classifier: Programming Language :: Python :: 3.10
Classifier: Programming Language :: Python :: 3.11
Classifier: Programming Language :: Python :: 3.12
Classifier: Topic :: Utilities
Requires-Python: >=3.10
Provides-Extra: dev
Requires-Dist: flake8; extra == 'dev'
Requires-Dist: numpy; extra == 'dev'
Requires-Dist: pytest; extra == 'dev'
Requires-Dist: pytest-cov; extra == 'dev'
Requires-Dist: pytest-mock; extra == 'dev'
Requires-Dist: towncrier; extra == 'dev'
